masonite_permission/MasonitePermission.py
masonite_permission/__init__.py
masonite_permission/config/masonite_permission.py
masonite_permission/exceptions/__init__.py
masonite_permission/migrations/create_permissions_table.py
masonite_permission/mixins/__init__.py
masonite_permission/mixins/has_permissions.py
masonite_permission/mixins/has_roles.py
masonite_permission/models/__init__.py
masonite_permission/models/permission.py
masonite_permission/models/role.py
masonite_permission/providers/PermissionProvider.py
masonite_permission/providers/__init__.py
masonite_permission-1.0.0.dist-info/LICENSE
masonite_permission-1.0.0.dist-info/METADATA
masonite_permission-1.0.0.dist-info/WHEEL
masonite_permission-1.0.0.dist-info/top_level.txt
masonite_permission-1.0.0.dist-info/RECORD
